PyOfficeTools/__init__.py
PyOfficeTools/example.py
pyofficetools-0.0.4.dist-info/METADATA
pyofficetools-0.0.4.dist-info/WHEEL
pyofficetools-0.0.4.dist-info/licenses/LICENSE
pyofficetools-0.0.4.dist-info/RECORD
