Metadata-Version: 2.4
Name: PyOfficeTools
Version: 0.0.4
Summary: 基于 Python 开发的自动化 office 工具包
Project-URL: Gitee, https://gitee.com/Muzi-Li-Chine/PyOfficeTools.git
Project-URL: Issues, https://gitee.com/Muzi-Li-Chine/PyOfficeTools/issues
Author-email: muzili <1537080775@qq.com>
License-Expression: MIT
License-File: LICENSE
Classifier: Operating System :: OS Independent
Classifier: Programming Language :: Python :: 3
Requires-Python: >=3.8
